bearsh
