Metadata-Version: 1.0
Name: bearsh
Version: 0.1.3
Summary: IPython shell extension for coala
Home-page: UNKNOWN
Author: Stefan Zimmermann
Author-email: user@zimmermann.co
License: AGPLv3
Platform: UNKNOWN
